{"2StGsFEhFNyhzEunVCjmVg==":"capture-1900x1031.png","iQiOXlQa6JtGR4p7NM8Gmw==":"screenshot%20(2)-1920x1080.png","9jVyhIDbKEPvxhwE0oaceA==":"photo_2023-04-22_18-25-49-591x1280.jpg","80AiLk5CFLXC3axlP+RW1A==":"photo_2023-05-07_14-16-18-590x1280.jpg","SuNrYugYjHENe29SjtRk2g==":"photo_2023-04-22_18-33-57-591x1280.jpg","DxAiCP3dDajvYvKmytNHrg==":"photo_2023-05-07_14-16-19-591x1280.jpg","biubTjRDQ0j0tmcdOycHxA==":"photo_2023-05-07_14-16-20-591x1280.jpg","WHIKSUG+wGDanlFAmo6uHA==":"screenshot_2023-04-22-18-43-16-414_org.telegram.messenger-820x1777.jpg","+kZ4CNI3tqxMCXiz+L6y8w==":"3.jpeg","vFMylMcodS+TuOEiNorhww==":"screenshot%20(3)-1288x725.png","Wu5QUyPEC3FqXNsaN0Qz5A==":"screenshot%20(3)-1288x725.png","oRykAiO0rUD++7AmPeEwUg==":"background1.jpg","n1dx+NZv3qks526xC0hZ5Q==":"background13.jpg","A3HZhqLDUxD3tl/2gYb41Q==":"screenshot%20(1)-1920x1080.png","9ASMBYx9VcBUNHfzbjQ01g==":"picture1-96x32.png","RuDOzOd+Bho///UOJ85AkA==":"trader%20sk%20logo-288x96.png","JzWeYpwYEuVMqwcrBYSMrg==":"mbr-1920x1150.jpg","BbDRyT30bxLxhKow03iS2Q==":"trader%20sk%20logo-1500x500.png","3WU+Du7ZdW4eq6j1wS3BTA==":"entering-1900x1031.png","mPTjhYv5pD65BzJTvo+D+Q==":"roi-1900x1031.png","8EU7y/mexAcK44Fdmq9nlQ==":"roi1-1900x1031.png","lXIgdBVptu9FGbsuvTfQVQ==":"entering-1-1900x1031.png","DpBFll8VuUmmewoBbBkdyQ==":"new-1900x1031.png","fmVdVFe9dK8XSgFXSZem3A==":"paytm-501x507.png","Vb7GgbMoe0curpGYBParsg==":"background3.jpg","mHORW0ykdG8H6CquiAAlBA==":"background4.jpg"}